disropt/__init__.py
disropt/agents/__init__.py
disropt/agents/agent.py
disropt/algorithms/__init__.py
disropt/algorithms/admm.py
disropt/algorithms/algorithm.py
disropt/algorithms/asymm.py
disropt/algorithms/consensus.py
disropt/algorithms/constraintexchange.py
disropt/algorithms/dual_decomp.py
disropt/algorithms/dual_subgradient.py
disropt/algorithms/gradient_tracking.py
disropt/algorithms/misc.py
disropt/algorithms/primal_decomp.py
disropt/algorithms/primal_decomp_milp.py
disropt/algorithms/setmembership.py
disropt/algorithms/subgradient.py
disropt/communicators/__init__.py
disropt/communicators/communicators.py
disropt/constraints/__init__.py
disropt/constraints/constraints.py
disropt/constraints/extended_constraint.py
disropt/constraints/projection_sets.py
disropt/functions/__init__.py
disropt/functions/abs.py
disropt/functions/abstract_function.py
disropt/functions/affine_form.py
disropt/functions/constant.py
disropt/functions/exp.py
disropt/functions/extended_function.py
disropt/functions/log.py
disropt/functions/logistic.py
disropt/functions/max.py
disropt/functions/min.py
disropt/functions/norm.py
disropt/functions/power.py
disropt/functions/quadratic_form.py
disropt/functions/square.py
disropt/functions/squared_norm.py
disropt/functions/stochastic_function.py
disropt/functions/submodular_func.py
disropt/functions/utilities.py
disropt/functions/variable.py
disropt/problems/__init__.py
disropt/problems/constraint_coupled_problem.py
disropt/problems/conv_milp.py
disropt/problems/linear_problem.py
disropt/problems/milp.py
disropt/problems/problem.py
disropt/problems/projection_problem.py
disropt/problems/quadratic_problem.py
disropt/problems/utilities.py
disropt/tests/__init__.py
disropt/tests/test_functions.py
disropt/utils/LP_utils.py
disropt/utils/__init__.py
disropt/utils/graph_constructor.py
disropt/utils/utilities.py
disropt-0.1.9.dist-info/LICENSE
disropt-0.1.9.dist-info/METADATA
disropt-0.1.9.dist-info/WHEEL
disropt-0.1.9.dist-info/top_level.txt
disropt-0.1.9.dist-info/RECORD
