Metadata-Version: 2.1
Name: disropt
Version: 0.1.9
Summary: DISROPT: a python framework for distributed optimization
Home-page: https://opt4smart.github.io/disropt/
Author: Francesco Farina, Andrea Camisa, Andrea Testa, Ivano Notarnicola, Giuseppe Notarstefano
Author-email: franc.farina@unibo.it
License: UNKNOWN
Platform: UNKNOWN
Classifier: Development Status :: 3 - Alpha
Classifier: License :: OSI Approved :: GNU General Public License v3 (GPLv3)
Classifier: Programming Language :: Python :: 3
Classifier: Operating System :: OS Independent
License-File: LICENSE
Requires-Dist: autograd (>=1.3)
Requires-Dist: cvxopt (>=1.2.3)
Requires-Dist: cvxpy (>=1.0.25)
Requires-Dist: mpi4py (>=3.0.1)
Requires-Dist: numpy (>=1.16.3)
Requires-Dist: osqp (>=0.6.1)
Requires-Dist: scipy (>=1.2.1)
Requires-Dist: dill (>=0.3.0)
